schemahybrid_translation/__init__.py
schemahybrid_translation/api.py
schemahybrid_translation/fields.py
schemahybrid_translation/tests.py
django_schemahybrid_translation-0.1.4.dist-info/LICENSE.txt
django_schemahybrid_translation-0.1.4.dist-info/METADATA
django_schemahybrid_translation-0.1.4.dist-info/WHEEL
django_schemahybrid_translation-0.1.4.dist-info/top_level.txt
django_schemahybrid_translation-0.1.4.dist-info/RECORD
